[{
    "code": "4401",
    "name": "广州市",
    "cnt": 4044
  }, {
    "code": "440103",
    "name": "荔湾区",
    "cnt": 2464
  }, {
    "code": "440104",
    "name": "越秀区",
    "cnt": 2351
  }, {
    "code": "440105",
    "name": "海珠区",
    "cnt": 390
  }, {
    "code": "440106",
    "name": "天河区",
    "cnt": 4933
  }, {
    "code": "440111",
    "name": "白云区",
    "cnt": 503
  }, {
    "code": "440112",
    "name": "黄埔区",
    "cnt": 3141
  }, {
    "code": "440113",
    "name": "番禺区",
    "cnt": 467
  }, {
    "code": "440114",
    "name": "花都区",
    "cnt": 1002
  }, {
    "code": "440115",
    "name": "南沙区",
    "cnt": 2201
  }, {
    "code": "440183",
    "name": "增城区",
    "cnt": 427
  }, {
    "code": "440184",
    "name": "从化区",
    "cnt": 361
  }]
